diisco/__init__.py
diisco/constants.py
diisco/diisco.py
diisco/gaussian_process.py
diisco/guides.py
diisco/math_ops.py
diisco/names.py
diisco/prior_f_model.py
diisco/utils.py
diisco-0.1.2.dist-info/LICENSE
diisco-0.1.2.dist-info/METADATA
diisco-0.1.2.dist-info/WHEEL
diisco-0.1.2.dist-info/top_level.txt
diisco-0.1.2.dist-info/RECORD
