Metadata-Version: 2.1
Name: diisco
Version: 0.1.2
Summary: A probabilistic programming method to characterize dynamic cellular interactions in longitudinal scRNA-seq data.
Home-page: https://github.com/velezbeltran/diisco
Author: Nicolas Beltran-Velez
Author-email: nb2838@columbia.edu
License: MIT license
Keywords: diisco
Classifier: Development Status :: 2 - Pre-Alpha
Classifier: Intended Audience :: Developers
Classifier: License :: OSI Approved :: MIT License
Classifier: Natural Language :: English
Classifier: Programming Language :: Python :: 3
Classifier: Programming Language :: Python :: 3.6
Classifier: Programming Language :: Python :: 3.7
Classifier: Programming Language :: Python :: 3.8
Requires-Python: >=3.6
License-File: LICENSE
Requires-Dist: pyro-ppl
Requires-Dist: numpy
Requires-Dist: pandas
Requires-Dist: torch
Requires-Dist: scikit-learn
Requires-Dist: scipy
Requires-Dist: matplotlib
Requires-Dist: seaborn
